{"is_source_file": false, "format": "", "description": "", "external_files": [], "external_methods": [], "published": [], "classes": [], "methods": [], "calls": [], "search-terms": [], "state": 2, "file_id": 18, "knowledge_revision": 37, "git_revision": "8b9d8be209a99b1cf875e6b755a7934f2fbf22a3", "hash": "01baab25e7c57e65c9edc86e42c126e8", "format-version": 4, "code-base-name": "tic_tac_toe_frontend", "filename": "tic_tac_toe_frontend/package.json", "revision_history": [{"37": "8b9d8be209a99b1cf875e6b755a7934f2fbf22a3"}]}